dost_cat/__init__.py
dost_cat/dost_cat.py
dost_cat-0.1.0.dist-info/licenses/LICENSE
dost_cat-0.1.0.dist-info/METADATA
dost_cat-0.1.0.dist-info/WHEEL
dost_cat-0.1.0.dist-info/top_level.txt
dost_cat-0.1.0.dist-info/RECORD
