Metadata-Version: 2.4
Name: dost_cat
Version: 0.1.0
Summary: Easy a DOS
Author-email: HebeleKedi <muhammedefekayha@gmail.com>
License: MIT
Requires-Python: >=3.7
License-File: LICENSE
Dynamic: license-file
